itk/Configuration/ShapeConfig.py
itk/Configuration/Shape_snake_case.py
itk/ShapePython.py
itk/_ShapePython.abi3.so
itk/itkMeshProcrustesAlignFilterPython.py
itk_shape-0.4.0.dist-info/METADATA
itk_shape-0.4.0.dist-info/WHEEL
itk_shape-0.4.0.dist-info/entry_points.txt
itk_shape-0.4.0.dist-info/licenses/LICENSE
itk_shape-0.4.0.dist-info/RECORD
